good_redis/__init__.py
good_redis/_client.py
good_redis/_dictproxy.py
good_redis-0.2.8.dist-info/METADATA
good_redis-0.2.8.dist-info/WHEEL
good_redis-0.2.8.dist-info/RECORD
