Metadata-Version: 2.4
Name: good-redis
Version: 0.2.8
Summary: Good Kiwi Redis Library
Author-email: Chris Goddard <chris@goodkiwi.llc>
Requires-Python: >=3.12
Requires-Dist: good-common
Requires-Dist: redis>=6.2.0
